{
  "version": 1,
  "file": "org-3-uploads-stage.study_410.cage_4481.2025-08-01.22.32.mp4",
  "num_frames": 1800,
  "labels": {
    "0": {},
    "1": {
      "turn_left": [
        {
          "start": 1097,
          "end": 1104,
          "present": true
        },
        {
          "start": 1107,
          "end": 1109,
          "present": true
        },
        {
          "start": 1111,
          "end": 1111,
          "present": true
        },
        {
          "start": 1113,
          "end": 1117,
          "present": true
        },
        {
          "start": 1154,
          "end": 1167,
          "present": true
        },
        {
          "start": 1225,
          "end": 1265,
          "present": false
        },
        {
          "start": 1295,
          "end": 1304,
          "present": false
        },
        {
          "start": 1307,
          "end": 1309,
          "present": false
        },
        {
          "start": 1313,
          "end": 1325,
          "present": false
        },
        {
          "start": 1366,
          "end": 1384,
          "present": false
        },
        {
          "start": 1394,
          "end": 1398,
          "present": true
        },
        {
          "start": 1400,
          "end": 1410,
          "present": true
        },
        {
          "start": 1439,
          "end": 1449,
          "present": false
        },
        {
          "start": 1451,
          "end": 1451,
          "present": false
        },
        {
          "start": 1453,
          "end": 1454,
          "present": false
        },
        {
          "start": 1456,
          "end": 1483,
          "present": false
        },
        {
          "start": 1485,
          "end": 1485,
          "present": false
        }
      ]
    },
    "2": {}
  },
  "unfragmented_labels": {
    "0": {},
    "1": {
      "turn_left": [
        {
          "start": 1097,
          "end": 1117,
          "present": true
        },
        {
          "start": 1153,
          "end": 1167,
          "present": true
        },
        {
          "start": 1225,
          "end": 1265,
          "present": false
        },
        {
          "start": 1295,
          "end": 1325,
          "present": false
        },
        {
          "start": 1365,
          "end": 1384,
          "present": false
        },
        {
          "start": 1394,
          "end": 1410,
          "present": true
        },
        {
          "start": 1439,
          "end": 1489,
          "present": false
        }
      ]
    },
    "2": {}
  },
  "metadata": {
    "project": {},
    "video": {
      "assign_id_s3_url": "s3://org-3-uploads-prod/pipeline/study_410/2025v3.3/stream/cage_4481/2025-08-01/22.32/org.murine.assign-id.top:v3.3/assign-id.top.parquet",
      "cage_id": 4481,
      "date": "2025-08-01",
      "org_id": 3,
      "start_time": "22.32",
      "study_id": 410,
      "video_s3_url": "s3://org-3-uploads-prod/study/study_410/cage_4481/video/2025-08-01/22.32.top.mp4"
    }
  },
  "external_identities": {
    "0": "S2",
    "1": "S3",
    "2": "S4"
  },
  "labeler": "gbeane"
}